AUTHORS.rst
CHANGELOG.rst
LICENSE
MANIFEST.in
README.rst
requirements-dev.txt
requirements.txt
setup.cfg
setup.py
./clru/lrucache/lrucache_cy028_compat.h
clru/VERSION
clru/__init__.py
clru.egg-info/PKG-INFO
clru.egg-info/SOURCES.txt
clru.egg-info/dependency_links.txt
clru.egg-info/not-zip-safe
clru.egg-info/requires.txt
clru.egg-info/top_level.txt
clru/cuckoocache/__init__.py
clru/cuckoocache/cycuckoocache.pxd
clru/cuckoocache/cycuckoocache.pyx
clru/cuckoocache/pycuckoocache.py
clru/lrucache/__init__.py
clru/lrucache/cylrucache.pxd
clru/lrucache/cylrucache.pyx
clru/lrucache/pylrucache.py