Metadata-Version: 2.1
Name: clru
Version: 0.1.2
Summary: Cython LRU Structures
Home-page: https://github.com/klaussfreire/clru
Author: Claudio Freire
Author-email: klaussfreire@gmail.com
License: LGPLv3
Platform: UNKNOWN
Classifier: Development Status :: 4 - Beta
Classifier: Intended Audience :: Developers
Classifier: License :: OSI Approved :: GNU Lesser General Public License v3 (LGPLv3)
Classifier: Programming Language :: Python
Classifier: Programming Language :: Cython
Classifier: Programming Language :: Python :: 2
Classifier: Programming Language :: Python :: 3
Classifier: Topic :: Software Development :: Libraries
Classifier: Operating System :: OS Independent
Provides-Extra: dev
Provides-Extra: dev-strict
